lyriks/__init__.py
lyriks/__main__.py
lyriks/cli.py
lyriks/core/__init__.py
lyriks/core/audio_processor.py
lyriks/core/ffmpeg.py
lyriks/core/gemini.py
lyriks/core/spinner.py
lyriks/core/video_generator_mp.py
lyriks/core/video_generator_ps2.py
lyriks/core/youtube.py
lyriks/tests/test_video_generator.py
lyriks_video-0.6.2.dist-info/licenses/LICENSE
lyriks_video-0.6.2.dist-info/METADATA
lyriks_video-0.6.2.dist-info/WHEEL
lyriks_video-0.6.2.dist-info/top_level.txt
lyriks_video-0.6.2.dist-info/RECORD
