Metadata-Version: 2.4
Name: lyriks-video
Version: 0.6.2
Summary: Automated lyrics video generator
Author-email: simon0302010 <simon0302010@gmail.com>
License-Expression: GPL-3.0
Project-URL: Homepage, https://github.com/simon0302010/Lyriks
Classifier: Operating System :: POSIX :: Linux
Classifier: Operating System :: Microsoft :: Windows
Requires-Python: <3.12,>=3.11
License-File: LICENSE
Requires-Dist: click
Requires-Dist: demucs
Requires-Dist: langdetect
Requires-Dist: onnxruntime
Requires-Dist: openai-whisper
Requires-Dist: soundfile
Requires-Dist: torch
Requires-Dist: torchaudio
Requires-Dist: whisper-timestamped
Requires-Dist: moviepy
Requires-Dist: iso639-lang
Requires-Dist: matplotlib
Requires-Dist: pysubs2
Requires-Dist: questionary
Requires-Dist: tqdm
Provides-Extra: youtube
Requires-Dist: google-api-python-client; extra == "youtube"
Requires-Dist: oauth2-client; extra == "youtube"
Requires-Dist: google_auth_oauthlib; extra == "youtube"
Dynamic: license-file
